{
  "chatUsers": [],
  "users": [
    {
      "is_admin": true,
      "first_name": "Sulaiman",
      "last_name": "Sagynaliev",
      "email": "sulaimanmind862@gmail.com",
      "password": "123",
      "password_confirm": "123",
      "groups": "JS-35",
      "tasks": {
        "board_1": [
          {
            "name": "ewfewfwef",
            "group": "",
            "points": "56789",
            "description": "iubuib",
            "isDone": false,
            "isChecked": false
          }
        ],
        "board_2": []
      },
      "points": 0,
      "coins": 0,
      "payedMonths": 1,
      "chat": [],
      "KPI": 0,
      "image": "https://ltdfoto.ru/images/2023/11/02/suli35c3d8797a91b2ec.jpg",
      "id": 1
    },
    {
      "is_admin": true,
      "first_name": "test",
      "last_name": "tester",
      "email": "test@gmail.com",
      "password": "123",
      "password_confirm": "123",
      "groups": "JS-36",
      "tasks": {
        "board_1": [
          {
            "name": "ewfewfwef",
            "group": "",
            "points": "56789",
            "description": "iubuib",
            "isDone": false,
            "isChecked": false
          }
        ],
        "board_2": []
      },
      "points": 0,
      "coins": 0,
      "payedMonths": 1,
      "chat": [],
      "KPI": 0,
      "image": "",
      "id": 2
    },
    {
      "is_admin": false,
      "first_name": "admin",
      "last_name": "admin",
      "email": "admin@gmail.com",
      "password": "123",
      "password_confirm": "123",
      "groups": "",
      "tasks": {
        "board_1": [
          {
            "name": "wefeuiwfhbui",
            "group": "JS-35",
            "points": "23456",
            "description": "weobewu",
            "isDone": false,
            "isChecked": false
          },
          {
            "name": "ewfewfwef",
            "group": "",
            "points": "56789",
            "description": "iubuib",
            "isDone": false,
            "isChecked": false
          }
        ],
        "board_2": []
      },
      "points": 0,
      "coins": 0,
      "payedMonths": 1,
      "chat": [],
      "KPI": 0,
      "image": "",
      "id": 3
    },
    {
      "is_admin": true,
      "first_name": "Malik",
      "last_name": "Vundiza",
      "email": "malikvundiz@gmail.com",
      "password": "0709301103",
      "password_confirm": "0709301103",
      "groups": "JS-35",
      "tasks": {
        "board_1": [
          {
            "name": "wefeuiwfhbui",
            "group": "JS-35",
            "points": "23456",
            "description": "weobewu",
            "isDone": false,
            "isChecked": false
          },
          {
            "name": "ewfewfwef",
            "group": "",
            "points": "56789",
            "description": "iubuib",
            "isDone": false,
            "isChecked": false
          }
        ],
        "board_2": []
      },
      "points": 0,
      "coins": 0,
      "payedMonths": 1,
      "chat": [],
      "KPI": 0,
      "image": "https://ltdfoto.ru/images/2023/11/02/malik2255891b90588218.jpg",
      "id": 4
    },
    {
      "is_admin": false,
      "first_name": "Amantur",
      "last_name": "Mendibaev",
      "email": "amantur@gmail.com",
      "password": "123",
      "password_confirm": "123",
      "groups": "JS-35",
      "tasks": {
        "board_1": [
          {
            "name": "ewfewfwef",
            "group": "",
            "points": "56789",
            "description": "iubuib",
            "isDone": false,
            "isChecked": false
          }
        ],
        "board_2": []
      },
      "points": 0,
      "coins": 0,
      "payedMonths": 1,
      "chat": [],
      "KPI": 0,
      "image": "https://ltdfoto.ru/images/2023/11/02/aman829b327ed58f6179.jpg",
      "id": 5
    },
    {
      "is_admin": false,
      "first_name": "Sabina",
      "last_name": "Stalbekova",
      "email": "Sabina@gmail.com",
      "password": "123",
      "password_confirm": "123",
      "groups": "JS-35",
      "tasks": {
        "board_1": [
          {
            "name": "ewfewfwef",
            "group": "",
            "points": "56789",
            "description": "iubuib",
            "isDone": false,
            "isChecked": false
          }
        ],
        "board_2": []
      },
      "points": 0,
      "coins": 0,
      "payedMonths": 1,
      "chat": [],
      "KPI": 0,
      "image": "https://ltdfoto.ru/images/2023/11/02/sabinab329611b289cdca3.jpg",
      "id": 6
    },
    {
      "is_admin": false,
      "first_name": "Atay",
      "last_name": "Amankulov",
      "email": "Atay@gmail.com",
      "password": "123",
      "password_confirm": "123",
      "groups": "JS-35",
      "tasks": {
        "board_1": [],
        "board_2": []
      },
      "points": 0,
      "coins": 0,
      "payedMonths": 1,
      "chat": [],
      "KPI": 0,
      "image": "https://ltdfoto.ru/images/2023/11/02/atayf6c20028eb2c0571.jpg",
      "id": 7
    },
    {
      "is_admin": false,
      "first_name": "Argen",
      "last_name": "Paisbekov",
      "email": "Argen@gmail.com",
      "password": "123",
      "password_confirm": "123",
      "groups": "JS-35",
      "tasks": {
        "board_1": [],
        "board_2": []
      },
      "points": 0,
      "coins": 0,
      "payedMonths": 1,
      "chat": [],
      "KPI": 0,
      "image": "https://ltdfoto.ru/images/2023/11/02/argen.jpg",
      "id": 8
    },
    {
      "is_admin": false,
      "first_name": "LikeMyrza",
      "last_name": "Foooterbekov",
      "email": "Beka@gmail.com",
      "password": "123",
      "password_confirm": "123",
      "groups": "JS-35",
      "tasks": {
        "board_1": [],
        "board_2": []
      },
      "points": 0,
      "coins": 0,
      "payedMonths": 1,
      "chat": [],
      "KPI": 0,
      "image": "https://ltdfoto.ru/images/2023/11/02/footerd3e6a7da50052d74.jpg",
      "id": 9
    },
    {
      "is_admin": false,
      "first_name": "Olesya",
      "last_name": "Kan",
      "email": "olesya@gmail.com",
      "password": "123",
      "password_confirm": "123",
      "groups": "JS-35",
      "tasks": {
        "board_1": [],
        "board_2": []
      },
      "points": 0,
      "coins": 0,
      "payedMonths": 1,
      "chat": [],
      "KPI": 0,
      "image": "https://ltdfoto.ru/images/2023/11/02/kanola639f8fbbceada1c.jpg",
      "id": 10
    },
    {
      "is_admin": false,
      "first_name": "Erkin",
      "last_name": "theGoat",
      "email": "erkin@gmail.com",
      "password": "123",
      "password_confirm": "123",
      "groups": "JS-35",
      "tasks": {
        "board_1": [],
        "board_2": []
      },
      "points": 0,
      "coins": 0,
      "payedMonths": 1,
      "chat": [],
      "KPI": 0,
      "image": "https://m.media-amazon.com/images/I/61FJspbWOlL._AC_UF1000,1000_QL80_.jpg",
      "id": 11
    },
    {
      "is_admin": false,
      "first_name": "Tilek",
      "last_name": "Bolotov",
      "email": "tilek@gmail.com",
      "password": "123",
      "password_confirm": "123",
      "groups": "JS-35",
      "tasks": {
        "board_1": [],
        "board_2": []
      },
      "points": 0,
      "coins": 0,
      "payedMonths": 1,
      "chat": [],
      "KPI": 0,
      "image": "https://ltdfoto.ru/images/2023/11/02/tilek244e643bf360858c.jpg",
      "id": 12
    }
  ],
  "tasks": [
    {
      "name": "ssgefsd",
      "group": "",
      "points": "3214",
      "description": "fesfef",
      "isDone": false,
      "isChecked": false,
      "id": 1
    },
    {
      "name": "test",
      "group": "",
      "points": "15",
      "description": "asfnkqwnfkqwnfl",
      "isDone": false,
      "isChecked": false,
      "id": 2
    },
    {
      "name": "Сделать клон Трелло",
      "group": "",
      "points": "100",
      "description": "Здесь должно быть описание",
      "isDone": false,
      "isChecked": false,
      "id": 3
    }
  ],
  "votings": [
    {
      "name": "",
      "week": "",
      "type": "",
      "descr": "",
      "id": 4
    }
  ]
}
